IPhreeqcPy.py
IPhreeqcPy-2024.2.2.data/data/IPhreeqc.dll
IPhreeqcPy-2024.2.2.data/data/README.rst
IPhreeqcPy-2024.2.2.data/data/databases/alkaline.dat
IPhreeqcPy-2024.2.2.data/data/databases/cemdata07.dat
IPhreeqcPy-2024.2.2.data/data/databases/ex15.dat
IPhreeqcPy-2024.2.2.data/data/databases/llnl.dat
IPhreeqcPy-2024.2.2.data/data/databases/mcatexch.dat
IPhreeqcPy-2024.2.2.data/data/databases/minteq.dat
IPhreeqcPy-2024.2.2.data/data/databases/minteq.v4.dat
IPhreeqcPy-2024.2.2.data/data/databases/phreeqc.dat
IPhreeqcPy-2024.2.2.data/data/databases/phreeqcU.dat
IPhreeqcPy-2024.2.2.data/data/databases/phreeqd.dat
IPhreeqcPy-2024.2.2.data/data/databases/pitzer.dat
IPhreeqcPy-2024.2.2.data/data/databases/wateq4f.dat
IPhreeqcPy-2024.2.2.dist-info/METADATA
IPhreeqcPy-2024.2.2.dist-info/WHEEL
IPhreeqcPy-2024.2.2.dist-info/top_level.txt
IPhreeqcPy-2024.2.2.dist-info/RECORD
