Metadata-Version: 2.1
Name: IPhreeqcPy
Version: 2024.2.2
Summary: Python wrapper for Iphreeqc
Author: Ravi A. Patel
Author-email: ravee.a.patel@gmail.com
License: LGPL V3
Project-URL: Documentation, https://iphreeqcpy.readthedocs.io/en/latest/
Project-URL: Source, https://github.com/raviapatel/IPhreeqcPy/tree/main
Platform: Windows
Platform: Linux
Classifier: Intended Audience :: Developers
Classifier: Intended Audience :: Science/Research
Classifier: Operating System :: Microsoft :: Windows
Classifier: Operating System :: POSIX :: Linux
Classifier: Intended Audience :: Science/Research
Classifier: Programming Language :: Python :: 3
Classifier: Programming Language :: Python :: 3.6
Classifier: Programming Language :: Python :: 3.7
Classifier: Programming Language :: Python :: 3.8
Classifier: Programming Language :: Python :: 3.9
Classifier: Programming Language :: Python :: 3.10
Classifier: Programming Language :: Python :: 3.11
Requires-Python: >=3.0
Requires-Dist: requests
Requires-Dist: numpy
